README.rst
setup.py
gelato/__init__.py
gelato.constants.egg-info/PKG-INFO
gelato.constants.egg-info/SOURCES.txt
gelato.constants.egg-info/dependency_links.txt
gelato.constants.egg-info/namespace_packages.txt
gelato.constants.egg-info/requires.txt
gelato.constants.egg-info/top_level.txt
gelato/constants/__init__.py
gelato/constants/applications.py
gelato/constants/base.py
gelato/constants/compare.py
gelato/constants/licenses.py
gelato/constants/payments.py
gelato/constants/platforms.py
gelato/constants/ratingsbodies.py
gelato/constants/regions.py
gelato/constants/reviewers.py
gelato/constants/search.py
gelato/constants/submit.py