Metadata-Version: 1.0
Name: gelato.constants
Version: 0.1.4
Summary: Gelato constants
Home-page: UNKNOWN
Author: UNKNOWN
Author-email: UNKNOWN
License: UNKNOWN
Platform: UNKNOWN
